CHANGES.txt
DEVGUIDE.txt
MANIFEST.in
README.txt
easy_install.py
ez_setup.py
launcher.c
pkg_resources.py
release.py
setup.cfg
setup.py
_markerlib/__init__.py
_markerlib/markers.py
docs/Makefile
docs/conf.py
docs/development.txt
docs/easy_install.txt
docs/formats.txt
docs/index.txt
docs/merge-faq.txt
docs/merge.txt
docs/pkg_resources.txt
docs/python3.txt
docs/releases.txt
docs/roadmap.txt
docs/setuptools.txt
docs/using.txt
docs/_templates/indexsidebar.html
docs/_theme/nature/theme.conf
docs/_theme/nature/static/nature.css_t
docs/_theme/nature/static/pygments.css
humblesetuptools.egg-info/PKG-INFO
humblesetuptools.egg-info/SOURCES.txt
humblesetuptools.egg-info/dependency_links.txt
humblesetuptools.egg-info/entry_points.txt
humblesetuptools.egg-info/requires.txt
humblesetuptools.egg-info/top_level.txt
humblesetuptools.egg-info/zip-safe
setuptools/__init__.py
setuptools/archive_util.py
setuptools/cli-32.exe
setuptools/cli-64.exe
setuptools/cli-arm-32.exe
setuptools/cli.exe
setuptools/compat.py
setuptools/depends.py
setuptools/dist.py
setuptools/extension.py
setuptools/gui-32.exe
setuptools/gui-64.exe
setuptools/gui-arm-32.exe
setuptools/gui.exe
setuptools/lib2to3_ex.py
setuptools/package_index.py
setuptools/py26compat.py
setuptools/py27compat.py
setuptools/py31compat.py
setuptools/sandbox.py
setuptools/script template (dev).py
setuptools/script template.py
setuptools/site-patch.py
setuptools/ssl_support.py
setuptools/svn_utils.py
setuptools/version.py
setuptools/command/__init__.py
setuptools/command/alias.py
setuptools/command/bdist_egg.py
setuptools/command/bdist_rpm.py
setuptools/command/bdist_wininst.py
setuptools/command/build_ext.py
setuptools/command/build_py.py
setuptools/command/develop.py
setuptools/command/easy_install.py
setuptools/command/egg_info.py
setuptools/command/install.py
setuptools/command/install_egg_info.py
setuptools/command/install_lib.py
setuptools/command/install_scripts.py
setuptools/command/launcher manifest.xml
setuptools/command/register.py
setuptools/command/rotate.py
setuptools/command/saveopts.py
setuptools/command/sdist.py
setuptools/command/setopt.py
setuptools/command/test.py
setuptools/command/upload_docs.py
setuptools/tests/__init__.py
setuptools/tests/doctest.py
setuptools/tests/entries-v10
